chep/__init__.py
chep/chep.py
chep-0.1.dist-info/LICENSE
chep-0.1.dist-info/METADATA
chep-0.1.dist-info/WHEEL
chep-0.1.dist-info/top_level.txt
chep-0.1.dist-info/RECORD
