Metadata-Version: 2.1
Name: chep
Version: 0.1
Summary: Un paquete para extraer el puerto SSH del servicio chep
Home-page: https://github.com/jose503/chep
Author: Jose Corcios
Author-email: corciosv@gmail.com
License: UNKNOWN
Platform: UNKNOWN
Classifier: Programming Language :: Python :: 3
Classifier: License :: OSI Approved :: MIT License
Classifier: Operating System :: OS Independent
Requires-Python: >=3.6
